{
    "Place.95c566ce-3d9b-4bfe-993c-29889bb29c65": {
        "id": "95c566ce-3d9b-4bfe-993c-29889bb29c65",
        "updated_at": "2023-08-09T23:38:51.133262",
        "created_at": "2023-08-09T23:38:51.132976",
        "description": "new place",
        "name": "Bar",
        "__class__": "Place"
    },
    "Place.fa3f85b8-0531-41a6-8447-edcea2c94863": {
        "id": "fa3f85b8-0531-41a6-8447-edcea2c94863",
        "updated_at": "2023-08-09T23:38:51.136151",
        "created_at": "2023-08-09T23:38:51.136139",
        "__class__": "Place"
    },
    "Review.282d4c93-3698-4fe9-9e75-d08b6388cba2": {
        "id": "282d4c93-3698-4fe9-9e75-d08b6388cba2",
        "updated_at": "2023-08-09T23:38:51.139063",
        "created_at": "2023-08-09T23:38:51.139049",
        "__class__": "Review"
    },
    "Amenity.92b0eb75-891e-4e8e-8473-6c4a7f749cfb": {
        "id": "92b0eb75-891e-4e8e-8473-6c4a7f749cfb",
        "updated_at": "2023-08-09T23:38:51.141194",
        "created_at": "2023-08-09T23:38:51.141179",
        "__class__": "Amenity"
    },
    "State.fdfc6c1e-d273-4af2-8b81-d18a96b305d2": {
        "id": "fdfc6c1e-d273-4af2-8b81-d18a96b305d2",
        "updated_at": "2023-08-09T23:38:51.142899",
        "created_at": "2023-08-09T23:38:51.142881",
        "__class__": "State"
    },
    "BaseModel.02369fc2-6097-438c-83bd-3fede2c9626d": {
        "id": "02369fc2-6097-438c-83bd-3fede2c9626d",
        "updated_at": "2023-08-09T23:39:17.534448",
        "created_at": "2023-08-09T23:39:17.534398",
        "name": "My First Model",
        "my_number": 89,
        "__class__": "BaseModel"
    },
    "User.5aa5e4af-51fa-47d0-864f-b52c891681ee": {
        "id": "5aa5e4af-51fa-47d0-864f-b52c891681ee",
        "updated_at": "2023-08-09T23:39:45.791540",
        "created_at": "2023-08-09T23:39:45.791525",
        "first_name": "hbttttttttttttttttttttttttt",
        "last_name": "Bar",
        "email": "airbnb@mail.com",
        "password": "root",
        "age": 4577,
        "__class__": "User"
    },
    "User.738c2b7c-56c0-4191-8a41-ced29f4b0dcb": {
        "id": "738c2b7c-56c0-4191-8a41-ced29f4b0dcb",
        "updated_at": "2023-08-09T23:39:45.793193",
        "created_at": "2023-08-09T23:39:45.793177",
        "first_name": "John",
        "email": "airbnb2@mail.com",
        "password": "root",
        "__class__": "User"
    }
}